ancalagon/__init__.py
ancalagon/app.py
ancalagon/request.py
ancalagon/resolver.py
ancalagon/responses/__init__.py
ancalagon/responses/base.py
ancalagon/responses/json.py
ancalagon/responses/stream_response.py
ancalagon/routes.py
ancalagon/url.py
ancalagon/utils.py
ancalagon-0.0.4a0.dist-info/LICENSE
ancalagon-0.0.4a0.dist-info/WHEEL
ancalagon-0.0.4a0.dist-info/METADATA
ancalagon-0.0.4a0.dist-info/RECORD
