Metadata-Version: 2.1
Name: ancalagon
Version: 0.0.4a0
Summary: The blackest ASGI framework
License: GPL-3.0
Author: Nimond
Author-email: dndnomin@gmail.com
Requires-Python: >=3.6,<4.0
Classifier: License :: OSI Approved :: GNU General Public License v3 (GPLv3)
Classifier: Programming Language :: Python :: 3
Classifier: Programming Language :: Python :: 3.6
Classifier: Programming Language :: Python :: 3.7
Classifier: Programming Language :: Python :: 3.8
Requires-Dist: multidict (==4.7.5)
